[
    {
        "template": {
            "list|10-20": [
                {
                    "head": "@image(50x50)",
                    "name|1": [
                        "@name",
                        "@cname"
                    ],
                    "guanzhu|100-400": 1,
                    "pic": "@image(690x380)",
                    "content": "@cparagraph(2,4)",
                    "author|1": [
                        "@cname",
                        "@name"
                    ],
                    "love|100-400": 1
                }
            ]
        },
        "data": {
            "list": [
                {
                    "head": "http://dummyimage.com/50x50",
                    "name": "Laura Walker",
                    "guanzhu": 384,
                    "pic": "http://dummyimage.com/690x380",
                    "content": "十作展养产器主住周团二意它治却代。电解开府分个完社节议活青消常。标调连列加真养确使进据将参气局机无酸。带下名决半龙多质生电四分果。",
                    "author": "Brian Perez",
                    "love": 371
                },
                {
                    "head": "http://dummyimage.com/50x50",
                    "name": "Linda Anderson",
                    "guanzhu": 160,
                    "pic": "http://dummyimage.com/690x380",
                    "content": "相话又根更间备了如老维专听。入时平至红且极身体条设四才流。",
                    "author": "王芳",
                    "love": 103
                },
                {
                    "head": "http://dummyimage.com/50x50",
                    "name": "Daniel Martinez",
                    "guanzhu": 300,
                    "pic": "http://dummyimage.com/690x380",
                    "content": "素很需外起观问无圆高色导物向而。人叫车程世育和根说发面为值好也。",
                    "author": "易军",
                    "love": 171
                },
                {
                    "head": "http://dummyimage.com/50x50",
                    "name": "李秀英",
                    "guanzhu": 391,
                    "pic": "http://dummyimage.com/690x380",
                    "content": "过道物积样区却花照条外机么只年少教书。什争计机间格电等路便内社用。理得发指带法儿所气白或状例内。",
                    "author": "Kenneth Clark",
                    "love": 298
                },
                {
                    "head": "http://dummyimage.com/50x50",
                    "name": "Donald White",
                    "guanzhu": 168,
                    "pic": "http://dummyimage.com/690x380",
                    "content": "问会及志治正加划保集置毛进制去。除天儿群争者人立内状影里管布求。",
                    "author": "吴桂英",
                    "love": 278
                },
                {
                    "head": "http://dummyimage.com/50x50",
                    "name": "叶芳",
                    "guanzhu": 180,
                    "pic": "http://dummyimage.com/690x380",
                    "content": "酸表世方风得关便务广声共管。但活较开各内近很美路选机拉圆拉千手经。七验民比单便如石金济把参合长她决。确除高采价口力整你一期般段切重治效特。",
                    "author": "Melissa Anderson",
                    "love": 291
                },
                {
                    "head": "http://dummyimage.com/50x50",
                    "name": "邓刚",
                    "guanzhu": 259,
                    "pic": "http://dummyimage.com/690x380",
                    "content": "正受革委新前派段目重布却装。县周劳低专产老题往来布产类除众争。合取候日片政流干当去争增向三历。",
                    "author": "Jeffrey Martin",
                    "love": 254
                },
                {
                    "head": "http://dummyimage.com/50x50",
                    "name": "Nancy Moore",
                    "guanzhu": 274,
                    "pic": "http://dummyimage.com/690x380",
                    "content": "线已革斗证世做感车白值美热又。与外器选多除路圆候公维下九我山意选较。省所和影满切机标路设音新集应集。",
                    "author": "David Thomas",
                    "love": 397
                },
                {
                    "head": "http://dummyimage.com/50x50",
                    "name": "潘磊",
                    "guanzhu": 300,
                    "pic": "http://dummyimage.com/690x380",
                    "content": "眼理拉却三民县业都场验必别总矿。院制实素物见想书程长布界积经。",
                    "author": "董敏",
                    "love": 122
                },
                {
                    "head": "http://dummyimage.com/50x50",
                    "name": "曾艳",
                    "guanzhu": 368,
                    "pic": "http://dummyimage.com/690x380",
                    "content": "干身院书其值她单快长次体光界称龙。约白及计白此型变九化目才叫员学建可法。间问压心建统指认接约六以华约。种她况它下王规题何世矿看团按们可。",
                    "author": "唐伟",
                    "love": 396
                },
                {
                    "head": "http://dummyimage.com/50x50",
                    "name": "Elizabeth Jones",
                    "guanzhu": 260,
                    "pic": "http://dummyimage.com/690x380",
                    "content": "业展命治种称得计包平路行只处也用。光信重她委收月同小达阶只年什。",
                    "author": "贾伟",
                    "love": 204
                },
                {
                    "head": "http://dummyimage.com/50x50",
                    "name": "Matthew Allen",
                    "guanzhu": 209,
                    "pic": "http://dummyimage.com/690x380",
                    "content": "数电具么组流革前加质治等查反候山。社路调计路劳月素种完行认清今所料传。",
                    "author": "赵伟",
                    "love": 308
                },
                {
                    "head": "http://dummyimage.com/50x50",
                    "name": "黄涛",
                    "guanzhu": 295,
                    "pic": "http://dummyimage.com/690x380",
                    "content": "准住传群为求须化红么者积治派日由明。些为论原们习而维节华收反油设较。",
                    "author": "Nancy Martin",
                    "love": 222
                },
                {
                    "head": "http://dummyimage.com/50x50",
                    "name": "沈静",
                    "guanzhu": 101,
                    "pic": "http://dummyimage.com/690x380",
                    "content": "象装级近提铁能制办每解更同养。型包任处决细此复回果比米则因族力。性许进确没亲但九三又着八转又统更林群。",
                    "author": "Nancy Thomas",
                    "love": 248
                },
                {
                    "head": "http://dummyimage.com/50x50",
                    "name": "Mark Hall",
                    "guanzhu": 109,
                    "pic": "http://dummyimage.com/690x380",
                    "content": "引主原八标做还那用管适队产白支议联。办标断来较按更道物百信器满例只府公。入万写青国才思照明压话权都少。老联情平白及四般无派间来都命。",
                    "author": "崔娟",
                    "love": 144
                }
            ]
        },
        "rurl": "/"
    }
]